LICENSE
MANIFEST.in
README.rst
pyproject.toml
setup.py
tilescopegui/__init__.py
tilescopegui/main.py
tilescopegui/py.typed
tilescopegui.egg-info/PKG-INFO
tilescopegui.egg-info/SOURCES.txt
tilescopegui.egg-info/dependency_links.txt
tilescopegui.egg-info/entry_points.txt
tilescopegui.egg-info/requires.txt
tilescopegui.egg-info/top_level.txt
tilescopegui/blueprints/__init__.py
tilescopegui/blueprints/home.py
tilescopegui/blueprints/strategies.py
tilescopegui/blueprints/tiling.py
tilescopegui/combinatorics/__init__.py
tilescopegui/combinatorics/rules.py
tilescopegui/combinatorics/strategies.py
tilescopegui/combinatorics/tilings.py
tilescopegui/combinatorics/verification.py
tilescopegui/factory/__init__.py
tilescopegui/factory/app.py
tilescopegui/factory/config.py
tilescopegui/factory/error_handler.py
tilescopegui/static/favicon.91ab5aeb.ico
tilescopegui/static/index.html
tilescopegui/static/src.61396b14.css
tilescopegui/static/src.7853af14.css
tilescopegui/static/src.a8ccbd32.js
tilescopegui/utils/__init__.py
tilescopegui/utils/constants.py
tilescopegui/utils/exceptions.py
tilescopegui/utils/parsing.py
tilescopegui/utils/paths.py
tilescopegui/utils/web.py